odoo/addons/pattern_import_export_custom_header/README.rst
odoo/addons/pattern_import_export_custom_header/__init__.py
odoo/addons/pattern_import_export_custom_header/__manifest__.py
odoo/addons/pattern_import_export_custom_header/i18n/fr.po
odoo/addons/pattern_import_export_custom_header/i18n/pattern_import_export_custom_header.pot
odoo/addons/pattern_import_export_custom_header/models/__init__.py
odoo/addons/pattern_import_export_custom_header/models/pattern_config.py
odoo/addons/pattern_import_export_custom_header/readme/CONTRIBUTORS.rst
odoo/addons/pattern_import_export_custom_header/readme/DESCRIPTION.rst
odoo/addons/pattern_import_export_custom_header/readme/USAGE.rst
odoo/addons/pattern_import_export_custom_header/security/ir.model.access.csv
odoo/addons/pattern_import_export_custom_header/static/description/index.html
odoo/addons/pattern_import_export_custom_header/tests/__init__.py
odoo/addons/pattern_import_export_custom_header/tests/test_custom_header.py
odoo/addons/pattern_import_export_custom_header/views/pattern_config.xml
odoo14_addon_pattern_import_export_custom_header-14.0.1.0.1.dist-info/METADATA
odoo14_addon_pattern_import_export_custom_header-14.0.1.0.1.dist-info/WHEEL
odoo14_addon_pattern_import_export_custom_header-14.0.1.0.1.dist-info/top_level.txt
odoo14_addon_pattern_import_export_custom_header-14.0.1.0.1.dist-info/RECORD
