Metadata-Version: 2.1
Name: odoo14-addon-pattern-import-export-custom-header
Version: 14.0.1.0.1
Summary: Allow to use custom headers names in export files
Home-page: https://github.com/shopinvader/pattern-import-export
Author: Akretion
License: AGPL-3
Platform: UNKNOWN
Classifier: Programming Language :: Python
Classifier: Framework :: Odoo
Classifier: Framework :: Odoo :: 14.0
Classifier: License :: OSI Approved :: GNU Affero General Public License v3
Requires-Python: >=3.6
Requires-Dist: odoo14-addon-pattern-import-export
Requires-Dist: odoo (<14.1dev,>=14.0a)
